diecast/__init__.py
diecast/config.py
diecast/decorator.py
diecast/error_utils.py
diecast/logging.py
diecast/mold.py
diecast/type_utils.py
py_diecast-0.2.1.dist-info/licenses/LICENSE
py_diecast-0.2.1.dist-info/METADATA
py_diecast-0.2.1.dist-info/WHEEL
py_diecast-0.2.1.dist-info/top_level.txt
py_diecast-0.2.1.dist-info/RECORD
