Metadata-Version: 2.4
Name: py-diecast
Version: 0.2.1
Summary: A Python tool to enforce type hints as runtime assertions.
Author-email: ToastX <toast_x@bytebot.site>
License-Expression: MIT
Project-URL: Homepage, https://github.com/GWUDCAP/diecast
Project-URL: Repository, https://github.com/GWUDCAP/diecast
Keywords: type hints,typing,runtime,assertions,validation,decorator,static analysis,dynamic analysis
Classifier: Development Status :: 4 - Beta
Classifier: Intended Audience :: Developers
Classifier: Operating System :: OS Independent
Classifier: Programming Language :: Python :: 3
Classifier: Programming Language :: Python :: 3.8
Classifier: Programming Language :: Python :: 3.9
Classifier: Programming Language :: Python :: 3.10
Classifier: Programming Language :: Python :: 3.11
Classifier: Programming Language :: Python :: 3.12
Classifier: Topic :: Software Development :: Libraries :: Python Modules
Classifier: Topic :: Software Development :: Quality Assurance
Requires-Python: >=3.8
License-File: LICENSE
Dynamic: license-file
